{
  "_date": "2026-06-09",
  "_dailyTrades": [],
  "_reportSent": false,
  "SPY": {
    "active": true,
    "signal": "CALL",
    "entryScore": 93,
    "entryPrice": 743.54,
    "entryTime": 1781011826427,
    "optionSymbol": "SPY260609C00745000",
    "strike": "745",
    "entryPremium": 1.03,
    "qty": 9,
    "orderId": "13710179-e221-4f15-b3d0-01c54836354b",
    "stopOrderId": "87652e39-789b-48a2-86fe-3f38ce967ff3",
    "peakPremium": 1.1,
    "currentStop": 0.721,
    "stopPhase": "initial",
    "breakEvenAnnounced": false,
    "bufferAnnounced": false,
    "trailingAnnounced": false,
    "entryMessageId": 408
  },
  "QQQ": {
    "active": true,
    "signal": "CALL",
    "entryScore": 83,
    "entryPrice": 722.22,
    "entryTime": 1781011826427,
    "optionSymbol": "QQQ260609C00723000",
    "strike": "723",
    "entryPremium": 2.46,
    "qty": 4,
    "orderId": "5967bdd4-0c9c-4409-bfd2-1529f3c4cadf",
    "stopOrderId": "bc271201-c053-4ad1-9c96-26dbbb0afd08",
    "peakPremium": 2.46,
    "currentStop": 1.722,
    "stopPhase": "initial",
    "breakEvenAnnounced": false,
    "bufferAnnounced": false,
    "trailingAnnounced": false,
    "entryMessageId": 409
  },
  "NVDA": {
    "active": false,
    "cooldownUntil": 1780944674349
  },
  "META": {
    "active": false,
    "cooldownUntil": 1780945696669
  },
  "AAPL": {
    "active": false,
    "cooldownUntil": 1780947195593
  }
}