{
  "_date": "2026-07-06",
  "_dailyTrades": [],
  "_reportSent": false,
  "_dailyLosses": 0,
  "_dailyTrades_count": 0,
  "_consecLosses": 0,
  "GLD": {
    "active": false,
    "exited": true,
    "cooldownUntil": 1783021227263,
    "lastSignal": "PUT",
    "lastExitTime": 1783020627263
  },
  "SPY": {
    "active": false,
    "exited": true,
    "cooldownUntil": 1783018875130,
    "lastSignal": "CALL",
    "lastExitTime": 1783018275130
  },
  "QQQ": {
    "active": false,
    "exited": true,
    "cooldownUntil": 1783002921855,
    "lastSignal": "CALL",
    "lastExitTime": 1783002321855
  },
  "IWM": {
    "active": false,
    "exited": true,
    "cooldownUntil": 1783008038309,
    "lastSignal": "CALL",
    "lastExitTime": 1783007438309
  }
}