{
  "_date": "2026-06-12",
  "_dailyTrades": [
    {
      "symbol": "NVDA",
      "signal": "CALL",
      "entryPremium": 1.33,
      "exitPremium": 1.3,
      "qty": 8,
      "pnl": -24.00000000000002,
      "pnlPct": -2.2556390977443628,
      "reason": "breakeven",
      "minutes": 1
    },
    {
      "symbol": "NVDA",
      "signal": "CALL",
      "entryPremium": 1.01,
      "exitPremium": 0.71,
      "qty": 11,
      "pnl": -330.00000000000006,
      "pnlPct": -29.702970297029708,
      "reason": "loss",
      "minutes": 1
    },
    {
      "symbol": "TSLA",
      "signal": "CALL",
      "entryPremium": 5.42,
      "exitPremium": 3.8,
      "qty": 2,
      "pnl": -324,
      "pnlPct": -29.88929889298893,
      "reason": "loss",
      "minutes": 1
    },
    {
      "symbol": "AAPL",
      "signal": "PUT",
      "entryPremium": 0.98,
      "exitPremium": 1.26,
      "qty": 12,
      "pnl": 336.00000000000006,
      "pnlPct": 28.571428571428577,
      "reason": "trailing",
      "minutes": 1
    },
    {
      "symbol": "QQQ",
      "signal": "PUT",
      "entryPremium": 4.19,
      "exitPremium": 4.18,
      "qty": 2,
      "pnl": -2.000000000000135,
      "pnlPct": -0.23866348448688962,
      "reason": "breakeven",
      "minutes": 2
    },
    {
      "symbol": "MSTR",
      "signal": "PUT",
      "entryPremium": 0.13,
      "exitPremium": 0.08,
      "qty": 90,
      "pnl": -450,
      "pnlPct": -38.46153846153847,
      "reason": "loss",
      "minutes": 2
    },
    {
      "symbol": "AAPL",
      "signal": "PUT",
      "entryPremium": 1.48,
      "exitPremium": 1.91,
      "qty": 7,
      "pnl": 301,
      "pnlPct": 29.054054054054053,
      "reason": "trailing",
      "minutes": 3
    },
    {
      "symbol": "SPY",
      "signal": "PUT",
      "entryPremium": 2.95,
      "exitPremium": 2.05,
      "qty": 3,
      "pnl": -270.0000000000001,
      "pnlPct": -30.508474576271194,
      "reason": "loss",
      "minutes": 7
    },
    {
      "symbol": "AAPL",
      "signal": "PUT",
      "entryPremium": 0.45,
      "exitPremium": 0.31,
      "qty": 26,
      "pnl": -364.00000000000006,
      "pnlPct": -31.11111111111111,
      "reason": "loss",
      "minutes": 1
    },
    {
      "symbol": "NVDA",
      "signal": "CALL",
      "entryPremium": 0.92,
      "exitPremium": 0.638333,
      "qty": 12,
      "pnl": -338.0004,
      "pnlPct": -30.615978260869564,
      "reason": "loss",
      "minutes": 2
    },
    {
      "symbol": "MSTR",
      "signal": "CALL",
      "entryPremium": 0.54,
      "exitPremium": 0.37,
      "qty": 21,
      "pnl": -357.00000000000006,
      "pnlPct": -31.481481481481488,
      "reason": "loss",
      "minutes": 2
    },
    {
      "symbol": "META",
      "signal": "PUT",
      "entryPremium": 2.21,
      "exitPremium": 1.39,
      "qty": 5,
      "pnl": -410.00000000000006,
      "pnlPct": -37.10407239819005,
      "reason": "loss",
      "minutes": 10
    },
    {
      "symbol": "AAPL",
      "signal": "PUT",
      "entryPremium": 0.56,
      "exitPremium": 0.56,
      "qty": 20,
      "pnl": 0,
      "pnlPct": 0,
      "reason": "breakeven",
      "minutes": 4
    }
  ],
  "_reportSent": false,
  "SPY": {
    "active": false,
    "cooldownUntil": 1781273295327,
    "lastSignal": "PUT"
  },
  "QQQ": {
    "active": false,
    "cooldownUntil": 1781272393699,
    "lastSignal": "PUT"
  },
  "NVDA": {
    "active": true,
    "signal": "CALL",
    "entryScore": 83,
    "entryPrice": 205.64,
    "entryTime": 1781274917909,
    "optionSymbol": "NVDA260612C00207500",
    "strike": "207.5",
    "entryPremium": 0.53,
    "qty": 21,
    "orderId": "7dc49ef7-6eb3-460d-870a-715aa46442f4",
    "stopOrderId": "86696d8b-e730-4b19-953c-78d7078d593c",
    "peakPremium": 0.56,
    "currentStop": 0.371,
    "stopPhase": "initial",
    "breakEvenAnnounced": false,
    "bufferAnnounced": false,
    "trailingAnnounced": false,
    "entryMessageId": 891
  },
  "TSLA": {
    "active": true,
    "signal": "PUT",
    "entryScore": 90,
    "entryPrice": 395.09,
    "entryTime": 1781274917909,
    "optionSymbol": "TSLA260612P00395000",
    "strike": "395",
    "entryPremium": 5.25,
    "qty": 2,
    "orderId": "fcba5ddc-90d0-482b-9e37-397fa3d5af77",
    "stopOrderId": "dddeb3ed-a048-418a-8020-f5ba7cd61e9a",
    "peakPremium": 5.25,
    "currentStop": 3.675,
    "stopPhase": "initial",
    "breakEvenAnnounced": false,
    "bufferAnnounced": false,
    "trailingAnnounced": false,
    "entryMessageId": 892
  },
  "META": {
    "active": false,
    "cooldownUntil": 1781275274509,
    "lastSignal": "PUT"
  },
  "AAPL": {
    "active": false,
    "cooldownUntil": 1781275224485,
    "lastSignal": "PUT"
  },
  "MSTR": {
    "active": true,
    "signal": "CALL",
    "entryScore": 95,
    "entryPrice": 124.05,
    "entryTime": 1781274917909,
    "optionSymbol": "MSTR260612C00130000",
    "strike": "130",
    "entryPremium": 0.29,
    "qty": 39,
    "orderId": "9f2b8613-9a9e-4e0e-81fb-5c45cf577998",
    "stopOrderId": "51910a6a-cddf-4328-8300-743375abe4d2",
    "peakPremium": 0.37,
    "currentStop": 0.29,
    "stopPhase": "breakeven",
    "breakEvenAnnounced": true,
    "bufferAnnounced": false,
    "trailingAnnounced": false,
    "entryMessageId": 894
  }
}