{
  "_date": "2026-07-20",
  "_dailyTrades": [
    {
      "symbol": "QQQ",
      "signal": "PUT",
      "window": "ORB_Pullback",
      "entryPremium": 2.6100000000000003,
      "exitPremium": 2.86,
      "qty": 4,
      "pnl": 99.99999999999983,
      "pnlPct": 9.578544061302665,
      "reason": "stop_hit",
      "minutes": 9,
      "entryTime": 1784556317368,
      "exitTime": 1784556858516,
      "strike": "702",
      "setup": "Pullback rejection at EMA9, near resistance 702.30"
    },
    {
      "symbol": "SPY",
      "signal": "PUT",
      "window": "ORB_Pullback",
      "entryPremium": 1.665,
      "exitPremium": 2.19,
      "qty": 6,
      "pnl": 314.99999999999994,
      "pnlPct": 31.531531531531527,
      "reason": "stop_hit",
      "minutes": 22,
      "entryTime": 1784556051320,
      "exitTime": 1784557396687,
      "strike": "746",
      "setup": "Pullback rejection at VWAP, near resistance 746.79"
    },
    {
      "symbol": "GLD",
      "signal": "PUT",
      "window": "ORB_Pullback",
      "entryPremium": 0.87,
      "exitPremium": 0.54,
      "qty": 8,
      "pnl": -263.99999999999994,
      "pnlPct": -37.93103448275862,
      "reason": "stop_hit",
      "minutes": 12,
      "entryTime": 1784556925316,
      "exitTime": 1784557636273,
      "strike": "367",
      "setup": "Pullback rejection at EMA9, near resistance 367.07"
    },
    {
      "symbol": "QQQ",
      "signal": "PUT",
      "window": "RECOVERED",
      "entryPremium": 2.37,
      "exitPremium": 1.57,
      "qty": 4,
      "pnl": -320,
      "pnlPct": -33.755274261603375,
      "reason": "recovered_stop",
      "minutes": 5,
      "entryTime": 1784557545972,
      "exitTime": 1784557847224,
      "strike": "701",
      "setup": "Recovered from Alpaca"
    },
    {
      "symbol": "GLD",
      "signal": "CALL",
      "window": "MidMorning_VWAP",
      "entryPremium": 0.5,
      "exitPremium": 0.7,
      "qty": 16,
      "pnl": 319.99999999999994,
      "pnlPct": 39.99999999999999,
      "reason": "stop_hit",
      "minutes": 12,
      "entryTime": 1784559637613,
      "exitTime": 1784560340671,
      "strike": "368",
      "setup": "Pullback bounce at VWAP, near support 367.19"
    },
    {
      "symbol": "SPY",
      "signal": "CALL",
      "window": "MidMorning_VWAP",
      "entryPremium": 1.1749999999999998,
      "exitPremium": 1.45,
      "qty": 10,
      "pnl": 275.0000000000001,
      "pnlPct": 23.40425531914895,
      "reason": "stop_hit",
      "minutes": 13,
      "entryTime": 1784560525337,
      "exitTime": 1784561297891,
      "strike": "745",
      "setup": "Pullback bounce at EMA9, near support 743.79"
    }
  ],
  "_reportSent": false,
  "_dailyLosses": 584,
  "_dailyTrades_count": 6,
  "_consecLosses": 0,
  "GLD": {
    "active": false,
    "exited": true,
    "cooldownUntil": 1784560941143,
    "lastSignal": "CALL",
    "lastExitTime": 1784560341143
  },
  "SPY": {
    "active": false,
    "exited": true,
    "cooldownUntil": 1784561898444,
    "lastSignal": "CALL",
    "lastExitTime": 1784561298444
  },
  "QQQ": {
    "active": false,
    "exited": true,
    "cooldownUntil": 1784558447467,
    "lastSignal": "PUT",
    "lastExitTime": 1784557847467
  },
  "IWM": {
    "active": true,
    "signal": "CALL",
    "window": "MidMorning_VWAP",
    "optionSymbol": "IWM260720C00294000",
    "strike": "294",
    "entryPremium": 0.385,
    "qty": 14,
    "entryTime": 1784562020703,
    "orderId": "3d5639fe-c80e-4851-864a-6fed258e10bd",
    "stopOrderId": null,
    "currentStop": 0.25025000000000003,
    "peakPremium": 0.48,
    "targetPct": 60,
    "stopPct": 35,
    "timeExitMin": 25,
    "entryMessageId": 2085,
    "reason": "Pullback bounce at VWAP, near support 293.47",
    "partial1Done": false,
    "bePromoted": false,
    "partial2Done": false,
    "trailing": false,
    "remainingQty": 14,
    "quickExitWindow": true,
    "lastPremium": 0.48
  },
  "_dailyPeakProfit": 603.179999999993,
  "_profitProtected": false,
  "_profitGuardNotified": false
}