{
  "SPY": {
    "signal": "PUT",
    "score": 55,
    "strengthAr": "متوسطة",
    "timestamp": 1780500634409
  },
  "QQQ": {
    "signal": "PUT",
    "score": 57,
    "strengthAr": "متوسطة",
    "timestamp": 1780500634830
  },
  "NVDA": {
    "signal": "PUT",
    "score": 53,
    "strengthAr": "متوسطة",
    "timestamp": 1780500635225
  },
  "TSLA": {
    "signal": "CALL",
    "score": 63,
    "strengthAr": "متوسطة",
    "timestamp": 1780500635612
  },
  "META": {
    "signal": "CALL",
    "score": 63,
    "strengthAr": "متوسطة",
    "timestamp": 1780500636006
  },
  "AAPL": {
    "signal": "PUT",
    "score": 83,
    "strengthAr": "قوية جداً",
    "timestamp": 1780500636402
  },
  "MSTR": {
    "signal": "PUT",
    "score": 68,
    "strengthAr": "قوية",
    "timestamp": 1780500636756
  }
}