{
  "_date": "2026-06-12",
  "_dailyTrades": [
    {
      "symbol": "NVDA",
      "signal": "CALL",
      "entryPremium": 1.33,
      "exitPremium": 1.3,
      "qty": 8,
      "pnl": -24.00000000000002,
      "pnlPct": -2.2556390977443628,
      "reason": "breakeven",
      "minutes": 1
    },
    {
      "symbol": "NVDA",
      "signal": "CALL",
      "entryPremium": 1.01,
      "exitPremium": 0.71,
      "qty": 11,
      "pnl": -330.00000000000006,
      "pnlPct": -29.702970297029708,
      "reason": "loss",
      "minutes": 1
    },
    {
      "symbol": "TSLA",
      "signal": "CALL",
      "entryPremium": 5.42,
      "exitPremium": 3.8,
      "qty": 2,
      "pnl": -324,
      "pnlPct": -29.88929889298893,
      "reason": "loss",
      "minutes": 1
    },
    {
      "symbol": "AAPL",
      "signal": "PUT",
      "entryPremium": 0.98,
      "exitPremium": 1.26,
      "qty": 12,
      "pnl": 336.00000000000006,
      "pnlPct": 28.571428571428577,
      "reason": "trailing",
      "minutes": 1
    },
    {
      "symbol": "QQQ",
      "signal": "PUT",
      "entryPremium": 4.19,
      "exitPremium": 4.18,
      "qty": 2,
      "pnl": -2.000000000000135,
      "pnlPct": -0.23866348448688962,
      "reason": "breakeven",
      "minutes": 2
    },
    {
      "symbol": "MSTR",
      "signal": "PUT",
      "entryPremium": 0.13,
      "exitPremium": 0.08,
      "qty": 90,
      "pnl": -450,
      "pnlPct": -38.46153846153847,
      "reason": "loss",
      "minutes": 2
    },
    {
      "symbol": "AAPL",
      "signal": "PUT",
      "entryPremium": 1.48,
      "exitPremium": 1.91,
      "qty": 7,
      "pnl": 301,
      "pnlPct": 29.054054054054053,
      "reason": "trailing",
      "minutes": 3
    },
    {
      "symbol": "SPY",
      "signal": "PUT",
      "entryPremium": 2.95,
      "exitPremium": 2.05,
      "qty": 3,
      "pnl": -270.0000000000001,
      "pnlPct": -30.508474576271194,
      "reason": "loss",
      "minutes": 7
    },
    {
      "symbol": "AAPL",
      "signal": "PUT",
      "entryPremium": 0.45,
      "exitPremium": 0.31,
      "qty": 26,
      "pnl": -364.00000000000006,
      "pnlPct": -31.11111111111111,
      "reason": "loss",
      "minutes": 1
    }
  ],
  "_reportSent": false,
  "SPY": {
    "active": false,
    "cooldownUntil": 1781273295327,
    "lastSignal": "PUT"
  },
  "QQQ": {
    "active": false,
    "cooldownUntil": 1781272393699,
    "lastSignal": "PUT"
  },
  "NVDA": {
    "active": true,
    "signal": "CALL",
    "entryScore": 93,
    "entryPrice": 206.56,
    "entryTime": 1781274037003,
    "optionSymbol": "NVDA260612C00207500",
    "strike": "207.5",
    "entryPremium": 0.92,
    "qty": 12,
    "orderId": "28f604ce-389a-4ecd-8f95-034bec844d45",
    "stopOrderId": "e2a39785-6cc3-4496-a8a9-196641b1df52",
    "peakPremium": 0.92,
    "currentStop": 0.644,
    "stopPhase": "initial",
    "breakEvenAnnounced": false,
    "bufferAnnounced": false,
    "trailingAnnounced": false,
    "entryMessageId": 881
  },
  "TSLA": {
    "active": false,
    "cooldownUntil": 1781272338487,
    "lastSignal": "CALL"
  },
  "META": {
    "active": true,
    "signal": "PUT",
    "entryScore": 90,
    "entryPrice": 564.68,
    "entryTime": 1781274037003,
    "optionSymbol": "META260612P00562500",
    "strike": "562.5",
    "entryPremium": 2.21,
    "qty": 5,
    "orderId": "f31abc1a-3482-4045-b6c9-6288c91f31b2",
    "stopOrderId": "93708233-3e25-4c4b-b44f-d4e2d25e6f45",
    "peakPremium": 2.21,
    "currentStop": 1.547,
    "stopPhase": "initial",
    "breakEvenAnnounced": false,
    "bufferAnnounced": false,
    "trailingAnnounced": false,
    "entryMessageId": 882
  },
  "AAPL": {
    "active": false,
    "cooldownUntil": 1781274436597,
    "lastSignal": "PUT"
  },
  "MSTR": {
    "active": true,
    "signal": "CALL",
    "entryScore": 83,
    "entryPrice": 121.39,
    "entryTime": 1781274037003,
    "optionSymbol": "MSTR260612C00125000",
    "strike": "125",
    "entryPremium": 0.54,
    "qty": 21,
    "orderId": "59bd2ad9-6f6d-4ad5-968d-065557ae9039",
    "stopOrderId": "119f6dd0-6128-4adf-8d90-f55af871b3a7",
    "peakPremium": 0.54,
    "currentStop": 0.378,
    "stopPhase": "initial",
    "breakEvenAnnounced": false,
    "bufferAnnounced": false,
    "trailingAnnounced": false,
    "entryMessageId": 883
  }
}